pybc_coinmonkey
pybc_coinserver
pybc_cointk
pybc_server
setup.py
pybc/AuthenticatedDictionary.py
pybc/Block.py
pybc/Blockchain.py
pybc/BlockchainProtocol.py
pybc/ClientFactory.py
pybc/Peer.py
pybc/PowAlgorithm.py
pybc/ServerFactory.py
pybc/State.py
pybc/StateComponent.py
pybc/StateMachine.py
pybc/TransactionalBlockchain.py
pybc/__init__.py
pybc/coin.py
pybc/emergency_crypto_munitions.py
pybc/science.py
pybc/sqliteshelf.py
pybc/transactions.py
pybc/util.py
pybc.egg-info/PKG-INFO
pybc.egg-info/SOURCES.txt
pybc.egg-info/dependency_links.txt
pybc.egg-info/requires.txt
pybc.egg-info/top_level.txt