Metadata-Version: 1.0
Name: pybc
Version: 0.6.3
Summary: Generic Blockchain Library
Home-page: https://bitbucket.org/interfect/pybc
Author: Adam Novak
Author-email: interfect@gmail.com
License: UNKNOWN
Platform: UNKNOWN
